MANIFEST.in
setup.py
Products/__init__.py
Products.PloneHotfix20121106.egg-info/PKG-INFO
Products.PloneHotfix20121106.egg-info/SOURCES.txt
Products.PloneHotfix20121106.egg-info/dependency_links.txt
Products.PloneHotfix20121106.egg-info/entry_points.txt
Products.PloneHotfix20121106.egg-info/namespace_packages.txt
Products.PloneHotfix20121106.egg-info/not-zip-safe
Products.PloneHotfix20121106.egg-info/requires.txt
Products.PloneHotfix20121106.egg-info/top_level.txt
Products/PloneHotfix20121106/README.txt
Products/PloneHotfix20121106/__init__.py
Products/PloneHotfix20121106/allow_module.py
Products/PloneHotfix20121106/at_download.py
Products/PloneHotfix20121106/atat.py
Products/PloneHotfix20121106/crypto_oracle.py
Products/PloneHotfix20121106/crypto_oracle_p3.py
Products/PloneHotfix20121106/crypto_oracle_protect.py
Products/PloneHotfix20121106/django_crypto.py
Products/PloneHotfix20121106/ftp.py
Products/PloneHotfix20121106/getNavigationRootObject.py
Products/PloneHotfix20121106/get_request_var_or_attr.py
Products/PloneHotfix20121106/gtbn.py
Products/PloneHotfix20121106/kssdevel.py
Products/PloneHotfix20121106/kupu_spellcheck.py
Products/PloneHotfix20121106/membership_tool.py
Products/PloneHotfix20121106/python_scripts.py
Products/PloneHotfix20121106/queryCatalog.py
Products/PloneHotfix20121106/random_string.py
Products/PloneHotfix20121106/registerConfiglet.py
Products/PloneHotfix20121106/renameObjectsByPaths.py
Products/PloneHotfix20121106/safe_html.py
Products/PloneHotfix20121106/setHeader.py
Products/PloneHotfix20121106/uid_catalog.py
Products/PloneHotfix20121106/utils.py
Products/PloneHotfix20121106/widget_traversal.py
docs/HISTORY.txt
docs/INSTALL.txt
docs/LICENSE.GPL
docs/LICENSE.txt