Metadata-Version: 1.0
Name: Products.PloneHotfix20121106
Version: 1.2
Summary: Various Plone hotfixes, 2012-11-06
Home-page: http://github.com/plone
Author: Plone Security Team
Author-email: security@plone.org
License: GPL
Keywords: plone security hotfix patch
Platform: UNKNOWN
Classifier: Framework :: Plone
Classifier: Programming Language :: Python
